xpdfpghljk/__init__.py
xpdfpghljk/__main__.py
xpdfpghljk/hello.c
xpdfpghljk/hello.cp38-win_amd64.pyd
xpdfpghljk-0.4.2.dist-info/METADATA
xpdfpghljk-0.4.2.dist-info/WHEEL
xpdfpghljk-0.4.2.dist-info/entry_points.txt
xpdfpghljk-0.4.2.dist-info/top_level.txt
xpdfpghljk-0.4.2.dist-info/RECORD
