Metadata-Version: 2.1
Name: xpdfpghljk
Version: 0.4.2
Summary: This is just a cython + packaging + cibuildwheel test
Author: Liam Pattinson
Requires-Python: >=3.8
